[
  {
    "id": "q1_b21",
    "question": "实施乡村振兴战略，是全面建设社会主义现代化国家的重大历史任务。乡村振兴的重点和重中之重是（ ）。",
    "options": [
      "A. 人才振兴",
      "B. 文化振兴",
      "C. 产业振兴",
      "D. 生态振兴"
    ],
    "correct_answer": "C",
    "explanation": "【考点】乡村振兴战略\n【解析】习近平总书记多次强调，产业振兴是乡村振兴的重中之重。只有产业兴旺，才能让农业经营有效益、成为有奔头的产业，才能留住人才，为乡村全面振兴提供坚实的物质基础。"
  },
  {
    "id": "q1_b22",
    "question": "扎实推进共同富裕是高质量发展的根本目的。在推进共同富裕的过程中，正确的路径和方法是（ ）。",
    "options": [
      "A. 尽力而为、量力而行",
      "B. 劫富济贫，实现绝对平均主义",
      "C. 优先解决分配问题，后解决发展问题",
      "D. 由政府大包大揽，提供无限度的福利兜底"
    ],
    "correct_answer": "A",
    "explanation": "【考点】共同富裕与民生治理\n【解析】推进共同富裕要坚持“尽力而为、量力而行”，把保障和改善民生建立在经济发展和财力可持续的基础之上，不能好高骛远，也不能搞“福利陷阱”。"
  },
  {
    "id": "q1_b23",
    "question": "科技自立自强是国家强盛之基、安全之要。当前我国在关键核心技术攻关上，明确提出要健全（ ）。",
    "options": [
      "A. 完全由市场主导的技术研发体制",
      "B. 新型举国体制",
      "C. 地方政府主导的区域创新体制",
      "D. 以跨国垄断企业为核心的协同机制"
    ],
    "correct_answer": "B",
    "explanation": "【考点】高质量发展（科技创新）\n【解析】党的二十大和二十届三中全会均强调，要健全新型举国体制，强化国家战略科技力量，优化配置创新资源，集中力量打赢关键核心技术攻坚战。"
  },
  {
    "id": "q1_b24",
    "question": "二十届三中全会指出，（ ）是推进中国式现代化的根本保证。",
    "options": [
      "A. 坚持以人民为中心",
      "B. 坚持全面依法治国",
      "C. 党的领导",
      "D. 坚持系统观念"
    ],
    "correct_answer": "C",
    "explanation": "【考点】二十届三中全会（政治理论）\n【解析】全会明确指出，党的领导是进一步全面深化改革、推进中国式现代化的根本保证。必须深刻领悟“两个确立”的决定性意义，做到“两个维护”。"
  },
  {
    "id": "q1_b25",
    "question": "在深化基层治理体制改革中，中央层面重拳整治形式主义，强调要为基层减负。以下做法属于“为基层减负”核心要求的是（ ）。",
    "options": [
      "A. 将行政执法权全部下放到村（社区）",
      "B. 严格控制面向基层的督查检查考核总量和频次",
      "C. 增加村级组织的“牌子”和考核台账以规范管理",
      "D. 要求基层干部全天候在线打卡留痕"
    ],
    "correct_answer": "B",
    "explanation": "【考点】民生与基层治理（形式主义整治）\n【解析】中央多次发文整治形式主义为基层减负，强调要大幅精简文件和会议，严格控制督查检查考核总量和频次，规范“属地管理”，纠治“指尖上的形式主义”（如过度留痕、打卡），让基层干部有更多时间精力抓落实。"
  },
  {
    "id": "q1_b26",
    "question": "发展新质生产力，必须坚持从实际出发，先立后破、因地制宜、分类指导。这就要求各地在发展时（ ）。",
    "options": [
      "A. 必须放弃传统产业，全面转向新兴产业",
      "B. 盲目跟风，全国一盘棋搞同一种高科技模式",
      "C. 结合自身资源禀赋、产业基础和科研条件有所选择",
      "D. 依靠财政补贴大力引进外地的高新技术企业"
    ],
    "correct_answer": "C",
    "explanation": "【考点】新质生产力\n【解析】习近平总书记强调，发展新质生产力不是忽视、放弃传统产业，要防止一哄而上、泡沫化，也不要搞一种模式。各地要坚持从实际出发，根据本地的资源禀赋、产业基础、科研条件等，有选择地推动新产业、新模式、新动能发展。"
  },
  {
    "id": "q1_b27",
    "question": "秦岭是我国的“中央水塔”，是中华民族的祖脉和中华文化的重要象征。陕西在生态保护方面必须牢记的“国之大者”是（ ）。",
    "options": [
      "A. 大力开发秦岭旅游资源以带动经济",
      "B. 当好秦岭生态卫士，把秦岭生态环境保护和修复工作摆上重要位置",
      "C. 在秦岭北麓大规模建设高档别墅区",
      "D. 将秦岭核心保护区的人口全部强制迁出"
    ],
    "correct_answer": "B",
    "explanation": "【考点】国家重大战略（陕西省情与生态）\n【解析】习近平总书记来陕考察时强调，秦岭违建是一个大教训。要当好秦岭生态卫士，决不能重蹈覆辙，决不能在历史上留下骂名。保护好秦岭生态环境，就是保护国家生态安全屏障，是“国之大者”。"
  },
  {
    "id": "q1_b28",
    "question": "马克思主义中国化时代化的最新成果是习近平新时代中国特色社会主义思想。推进马克思主义中国化时代化的根本途径是（ ）。",
    "options": [
      "A. 坚持以经济建设为中心",
      "B. 坚持把马克思主义基本原理同中国具体实际相结合、同中华优秀传统文化相结合",
      "C. 坚持对外开放的基本国策",
      "D. 坚持走和平发展道路"
    ],
    "correct_answer": "B",
    "explanation": "【考点】时政理论（“两个结合”）\n【解析】党的二十大报告指出，坚持和发展马克思主义，必须同中国具体实际相结合，必须同中华优秀传统文化相结合（即“两个结合”）。这是推进马克思主义中国化时代化的根本途径。"
  },
  {
    "id": "q1_b29",
    "question": "建设更高水平开放型经济新体制，我国当前对外开放的重点和战略方向正在从商品和要素流动型开放向（ ）转变。",
    "options": [
      "A. 技术和人才输出型开放",
      "B. 资本输出型开放",
      "C. 规则、规制、管理、标准等制度型开放",
      "D. 能源与资源主导型开放"
    ],
    "correct_answer": "C",
    "explanation": "【考点】二十届三中全会（对外开放）\n【解析】全会强调，稳步扩大制度型开放。我国对外开放正由商品和要素流动型开放（传统的引进来、走出去），向规则、规制、管理、标准等制度型开放全面拓展。"
  },
  {
    "id": "q1_b30",
    "question": "在陕西省推动高质量发展的实践中，被定位为全省创新驱动发展总平台和总源头的是（ ）。",
    "options": [
      "A. 杨凌农业高新技术产业示范区",
      "B. 秦创原创新驱动平台",
      "C. 西安高新技术产业开发区",
      "D. 关中平原城市群"
    ],
    "correct_answer": "B",
    "explanation": "【考点】陕西省情与高质量发展\n【解析】秦创原是陕西省最大的孵化器和科技成果转化“特区”，是全省创新驱动发展总平台和总源头，旨在打破科技与经济脱节的瓶颈，加速产业链和创新链深度融合。"
  },
  {
    "id": "q1_b31",
    "question": "绿色发展是高质量发展的底色，新质生产力本身就是绿色生产力。实现这一目标的必由之路是（ ）。",
    "options": [
      "A. 全面停止煤炭开采和使用",
      "B. 限制高耗能企业的一切生产活动",
      "C. 加快发展方式绿色转型，推进碳达峰碳中和",
      "D. 将重污染企业向中西部地区转移"
    ],
    "correct_answer": "C",
    "explanation": "【考点】高质量发展（绿色转型）\n【解析】新质生产力本身就是绿色生产力。必须加快发展方式绿色转型，助力碳达峰碳中和。A、B项属于运动式减碳和“一刀切”，D项是污染转移，均不符合科学的绿色转型要求。"
  },
  {
    "id": "q1_b32",
    "question": "二十届三中全会提出，（ ）是促进共同富裕、打造高品质生活的基础性工程。",
    "options": [
      "A. 城乡融合发展",
      "B. 健全保障和改善民生制度体系",
      "C. 深化医药卫生体制改革",
      "D. 完善生态文明制度体系"
    ],
    "correct_answer": "B",
    "explanation": "【考点】二十届三中全会（民生制度）\n【解析】在全面深化改革中，全会明确将“健全保障和改善民生制度体系”作为促进共同富裕、打造高品质生活的基础性工程，强调要解决好人民最关心最直接最现实的利益问题。"
  },
  {
    "id": "q1_b33",
    "question": "中央经济工作会议强调，当前我国经济恢复的基础尚不牢固，需求收缩、供给冲击、（ ）三重压力仍然较大。",
    "options": [
      "A. 出口下滑",
      "B. 通货膨胀",
      "C. 预期转弱",
      "D. 债务攀升"
    ],
    "correct_answer": "C",
    "explanation": "【考点】中央经济工作会议（宏观研判）\n【解析】“需求收缩、供给冲击、预期转弱”是党中央对近年来我国宏观经济运行面临突出矛盾的经典概括。其中，稳预期（预期转弱）是提振市场信心的关键。"
  },
  {
    "id": "q1_b34",
    "question": "党的建设伟大工程中，全面从严治党永远在路上。党自我净化、自我完善、自我革新、自我提高的强大武器是（ ）。",
    "options": [
      "A. 批评和自我批评",
      "B. 群众路线",
      "C. 理论联系实际",
      "D. 自我革命"
    ],
    "correct_answer": "D",
    "explanation": "【考点】政治理论（党的建设）\n【解析】勇于自我革命是中国共产党区别于其他政党的显著标志。全面从严治党是新时代党的自我革命的伟大实践。党的自我革命是跳出治乱兴衰历史周期率的第二个答案。"
  },
  {
    "id": "q1_b35",
    "question": "在城乡融合发展体制机制中，打破城乡二元结构、促进城乡共同繁荣的核心在于（ ）。",
    "options": [
      "A. 让城市资本无条件兼并农村土地",
      "B. 促进城乡要素平等交换、双向流动",
      "C. 取消农村户口，全部转为城市户口",
      "D. 集中发展特大城市，让农民进城"
    ],
    "correct_answer": "B",
    "explanation": "【考点】二十届三中全会（城乡融合）\n【解析】全会提出完善城乡融合发展体制机制。城乡融合的关键在于打破要素流动的壁垒，促进人才、土地、资金等要素在城乡之间平等交换、双向流动，进而缩小城乡差别。"
  },
  {
    "id": "q1_b36",
    "question": "文化自信是一个国家、一个民族发展中更基本、更深沉、更持久的力量。新时代文化建设的中心环节是（ ）。",
    "options": [
      "A. 繁荣发展文化事业和文化产业",
      "B. 培育和践行社会主义核心价值观",
      "C. 提高全社会文明程度",
      "D. 保护历史文化遗产"
    ],
    "correct_answer": "B",
    "explanation": "【考点】理论常识（文化建设）\n【解析】培育和践行社会主义核心价值观是凝魂聚气、强基固本的基础工程，也是新时代文化建设的中心环节和根本任务。"
  },
  {
    "id": "q1_b37",
    "question": "针对实体经济融资难、融资贵问题，中央强调金融要为经济社会发展提供高质量服务。金融工作的根本宗旨是（ ）。",
    "options": [
      "A. 追求金融机构利润最大化",
      "B. 推动金融业高水平对外开放",
      "C. 服务实体经济",
      "D. 防范化解系统性金融风险"
    ],
    "correct_answer": "C",
    "explanation": "【考点】中央经济工作会议（金融高质量发展）\n【解析】中央金融工作会议强调，高质量发展是全面建设社会主义现代化国家的首要任务，金融要为经济社会发展提供高质量服务，必须坚持把服务实体经济作为根本宗旨。"
  },
  {
    "id": "q1_b38",
    "question": "高标准农田建设是保障粮食安全的重要举措。中央一号文件明确提出，要逐步把（ ）全部建成高标准农田。",
    "options": [
      "A. 所有的林地和草地",
      "B. 永久基本农田",
      "C. 农村宅基地",
      "D. 荒山荒坡"
    ],
    "correct_answer": "B",
    "explanation": "【考点】国家重大战略（粮食安全）\n【解析】保障国家粮食安全的根本在耕地。中央明确要求，要坚决守住18亿亩耕地红线，逐步把永久基本农田全部建成高标准农田，确保口粮绝对安全。"
  },
  {
    "id": "q1_b39",
    "question": "深化行政体制改革，优化政府职责体系和组织结构，其最终目标是建设（ ）。",
    "options": [
      "A. 权威型政府",
      "B. 管理型政府",
      "C. 服务型政府",
      "D. 经营型政府"
    ],
    "correct_answer": "C",
    "explanation": "【考点】民生治理与行政体制\n【解析】转变政府职能，深化行政体制改革，其核心目标是建设人民满意的服务型政府。这意味着政府角色要从单纯的管理转向更多的公共服务提供和市场监管。"
  },
  {
    "id": "q1_b40",
    "question": "陕西在推进区域协调发展方面，提出了“三大区域”协同发展的战略格局。这三大区域指的是（ ）。",
    "options": [
      "A. 关中、陕北、陕南",
      "B. 西安、咸阳、宝鸡",
      "C. 渭南、延安、榆林",
      "D. 汉中、安康、商洛"
    ],
    "correct_answer": "A",
    "explanation": "【考点】陕西省情与区域协调\n【解析】陕西省立足省情，明确提出了“关中协同创新、陕北转型升级、陕南绿色循环”的发展定位，这是统筹全省三大自然地理区域（关中、陕北、陕南）协调发展的核心战略。"
  }
]